fenicsx_growth-0.1.0.dist-info/licenses/LICENSE
growth/__init__.py
growth/datacollector.py
growth/geometry.py
growth/growth.py
growth/material.py
growth/models/__init__.py
growth/models/kerchoff.py
growth/models/simple_stress.py
fenicsx_growth-0.1.0.dist-info/METADATA
fenicsx_growth-0.1.0.dist-info/WHEEL
fenicsx_growth-0.1.0.dist-info/top_level.txt
fenicsx_growth-0.1.0.dist-info/RECORD
