Metadata-Version: 2.4
Name: fenicsx-growth
Version: 0.1.0
Summary: Cardiac growth models for FEniCSx
Author-email: Henrik Finsberg <henriknf@simula.no>, Karl Munthe <karlfredrik@simula.no>
License: Copyright 2025 Computational Physiology at Simula Research Laboratory
Requires-Python: >=3.10.0
License-File: LICENSE
Requires-Dist: fenics-dolfinx
Requires-Dist: scifem
Provides-Extra: test
Requires-Dist: pytest; extra == "test"
Requires-Dist: pytest-cov; extra == "test"
Provides-Extra: docs
Requires-Dist: jupyter-book; extra == "docs"
Requires-Dist: jupytext; extra == "docs"
Requires-Dist: jupyter; extra == "docs"
Requires-Dist: pyvista[all]>=0.43.0; extra == "docs"
Requires-Dist: trame-vuetify; extra == "docs"
Requires-Dist: ipywidgets; extra == "docs"
Provides-Extra: all
Requires-Dist: fenicsx_growth[test]; extra == "all"
Requires-Dist: fenicsx_growth[docs]; extra == "all"
Dynamic: license-file
